mimosa/.DS_Store
mimosa/__init__.py
mimosa/abstract_model.py
mimosa/mimosa.py
mimosa/__pycache__/__init__.cpython-311.pyc
mimosa/__pycache__/__init__.cpython-312.pyc
mimosa/__pycache__/__init__.cpython-38.pyc
mimosa/__pycache__/abstract_model.cpython-311.pyc
mimosa/__pycache__/abstract_model.cpython-312.pyc
mimosa/__pycache__/abstract_model.cpython-38.pyc
mimosa/__pycache__/all_constraints.cpython-311.pyc
mimosa/__pycache__/mimosa.cpython-311.pyc
mimosa/__pycache__/mimosa.cpython-312.pyc
mimosa/__pycache__/mimosa.cpython-38.pyc
mimosa/common/__init__.py
mimosa/common/economics.py
mimosa/common/pyomo_utils.py
mimosa/common/units.py
mimosa/common/utils.py
mimosa/common/__pycache__/__init__.cpython-311.pyc
mimosa/common/__pycache__/__init__.cpython-312.pyc
mimosa/common/__pycache__/__init__.cpython-38.pyc
mimosa/common/__pycache__/economics.cpython-311.pyc
mimosa/common/__pycache__/economics.cpython-312.pyc
mimosa/common/__pycache__/economics.cpython-38.pyc
mimosa/common/__pycache__/pyomo_utils.cpython-311.pyc
mimosa/common/__pycache__/pyomo_utils.cpython-312.pyc
mimosa/common/__pycache__/pyomo_utils.cpython-38.pyc
mimosa/common/__pycache__/units.cpython-311.pyc
mimosa/common/__pycache__/units.cpython-312.pyc
mimosa/common/__pycache__/units.cpython-38.pyc
mimosa/common/__pycache__/utils.cpython-311.pyc
mimosa/common/__pycache__/utils.cpython-312.pyc
mimosa/common/__pycache__/utils.cpython-38.pyc
mimosa/common/config/__init__.py
mimosa/common/config/parseconfig.py
mimosa/common/config/__pycache__/__init__.cpython-311.pyc
mimosa/common/config/__pycache__/__init__.cpython-312.pyc
mimosa/common/config/__pycache__/__init__.cpython-38.pyc
mimosa/common/config/__pycache__/parseconfig.cpython-311.pyc
mimosa/common/config/__pycache__/parseconfig.cpython-312.pyc
mimosa/common/config/__pycache__/parseconfig.cpython-38.pyc
mimosa/common/config/utils/__init__.py
mimosa/common/config/utils/nested_dict.py
mimosa/common/config/utils/parsers.py
mimosa-0.2.6.dist-info/licenses/LICENSE
mimosa-0.2.6.dist-info/METADATA
mimosa-0.2.6.dist-info/WHEEL
mimosa-0.2.6.dist-info/top_level.txt
mimosa-0.2.6.dist-info/RECORD
