Metadata-Version: 2.4
Name: mimosa
Version: 0.2.6
Summary: MIMOSA: Integrated Assessment Model for Cost-Benefit Analysis
Home-page: https://utrechtuniversity.github.io/mimosa/
Author: Kaj-Ivar van der Wijst
Author-email: k.vanderwijst@uu.nl
License:                     GNU GENERAL PUBLIC LICENSE
Requires-Python: >=3.8
License-File: LICENSE
Requires-Dist: numpy>=1.22
Requires-Dist: pandas
Requires-Dist: pyomo
Requires-Dist: pint
Requires-Dist: pyyaml
Requires-Dist: scipy
Requires-Dist: networkx
Dynamic: author
Dynamic: author-email
Dynamic: description
Dynamic: description-content-type
Dynamic: home-page
Dynamic: license
Dynamic: license-file
Dynamic: requires-dist
Dynamic: requires-python
Dynamic: summary
